discorudo/__init__.py
discorudo/main.py
discorudo-1.7.dist-info/METADATA
discorudo-1.7.dist-info/WHEEL
discorudo-1.7.dist-info/top_level.txt
discorudo-1.7.dist-info/RECORD
